ibridges/__init__.py
ibridges/_version.py
ibridges/data_operations.py
ibridges/exception.py
ibridges/executor.py
ibridges/icat_columns.py
ibridges/interactive.py
ibridges/meta.py
ibridges/path.py
ibridges/permissions.py
ibridges/py.typed
ibridges/resources.py
ibridges/rules.py
ibridges/search.py
ibridges/session.py
ibridges/tickets.py
ibridges/util.py
ibridges/cli/__init__.py
ibridges/cli/__main__.py
ibridges/cli/base.py
ibridges/cli/config.py
ibridges/cli/data_operations.py
ibridges/cli/meta.py
ibridges/cli/navigation.py
ibridges/cli/other.py
ibridges/cli/shell.py
ibridges/cli/util.py
ibridges-2.0.1.dist-info/licenses/LICENSE
ibridges-2.0.1.dist-info/METADATA
ibridges-2.0.1.dist-info/WHEEL
ibridges-2.0.1.dist-info/entry_points.txt
ibridges-2.0.1.dist-info/top_level.txt
ibridges-2.0.1.dist-info/RECORD
