Metadata-Version: 2.4
Name: ibridges
Version: 2.0.1
Summary: Package for accessing data and metadata on iRODS servers.
Author-email: Christine Staiger <c.staiger@uu.nl>, Raoul Schram <r.d.schram@uu.nl>, Maarten Schermer <m.d.schermer@uu.nl>
License: MIT License
Project-URL: GitHub, https://github.com/iBridges-for-iRODS/iBridges
Project-URL: documentation, https://github.com/iBridges-for-iRODS/iBridges
Keywords: irods,data management,storage
Classifier: Programming Language :: Python :: 3
Classifier: Programming Language :: Python :: 3.8
Classifier: Programming Language :: Python :: 3.9
Classifier: Programming Language :: Python :: 3.10
Classifier: Programming Language :: Python :: 3.11
Classifier: Programming Language :: Python :: 3.12
Classifier: Programming Language :: Python :: 3.13
Classifier: Development Status :: 5 - Production/Stable
Classifier: License :: OSI Approved :: MIT License
Requires-Python: >=3.8
License-File: LICENSE
Requires-Dist: python-irodsclient!=3.1.0,>=2.0.0; python_version >= "3.9"
Requires-Dist: python-irodsclient!=3.1.0,<3.2,>=2.0.0; python_version < "3.9"
Requires-Dist: tqdm
Requires-Dist: importlib-metadata>=4.6; python_version < "3.10"
Provides-Extra: test
Requires-Dist: pylint; extra == "test"
Requires-Dist: pytest; extra == "test"
Requires-Dist: pytest-cov; extra == "test"
Requires-Dist: ruff; extra == "test"
Requires-Dist: mypy; extra == "test"
Requires-Dist: types-tqdm; extra == "test"
Provides-Extra: docs
Requires-Dist: sphinx<9; extra == "docs"
Requires-Dist: sphinx-rtd-theme; extra == "docs"
Requires-Dist: sphinxcontrib-napoleon; extra == "docs"
Requires-Dist: sphinx-autodoc-typehints; extra == "docs"
Requires-Dist: sphinx_inline_tabs; extra == "docs"
Requires-Dist: sphinx_copybutton; extra == "docs"
Requires-Dist: sphinx-argparse; extra == "docs"
Dynamic: license-file
